odoo8_addon_purchase_triple_discount-8.0.1.0.0.99.dev3-py3.8-nspkg.pth
odoo_addons/purchase_triple_discount/README.rst
odoo_addons/purchase_triple_discount/__init__.py
odoo_addons/purchase_triple_discount/__openerp__.py
odoo_addons/purchase_triple_discount/demo/purchase_order.xml
odoo_addons/purchase_triple_discount/i18n/de.po
odoo_addons/purchase_triple_discount/i18n/es.po
odoo_addons/purchase_triple_discount/i18n/es_MX.po
odoo_addons/purchase_triple_discount/i18n/es_PE.po
odoo_addons/purchase_triple_discount/i18n/fi.po
odoo_addons/purchase_triple_discount/i18n/fr.po
odoo_addons/purchase_triple_discount/i18n/hr.po
odoo_addons/purchase_triple_discount/i18n/it.po
odoo_addons/purchase_triple_discount/i18n/nl_NL.po
odoo_addons/purchase_triple_discount/i18n/pt_BR.po
odoo_addons/purchase_triple_discount/i18n/pt_PT.po
odoo_addons/purchase_triple_discount/i18n/purchase_triple_discount.pot
odoo_addons/purchase_triple_discount/i18n/ro.po
odoo_addons/purchase_triple_discount/i18n/sl.po
odoo_addons/purchase_triple_discount/models/__init__.py
odoo_addons/purchase_triple_discount/models/account_invoice.py
odoo_addons/purchase_triple_discount/models/purchase_order.py
odoo_addons/purchase_triple_discount/models/stock_move.py
odoo_addons/purchase_triple_discount/static/description/icon.png
odoo_addons/purchase_triple_discount/tests/__init__.py
odoo_addons/purchase_triple_discount/tests/test_purchase_discount.py
odoo_addons/purchase_triple_discount/views/purchase_view.xml
odoo8_addon_purchase_triple_discount-8.0.1.0.0.99.dev3.dist-info/METADATA
odoo8_addon_purchase_triple_discount-8.0.1.0.0.99.dev3.dist-info/WHEEL
odoo8_addon_purchase_triple_discount-8.0.1.0.0.99.dev3.dist-info/namespace_packages.txt
odoo8_addon_purchase_triple_discount-8.0.1.0.0.99.dev3.dist-info/top_level.txt
odoo8_addon_purchase_triple_discount-8.0.1.0.0.99.dev3.dist-info/RECORD
